prompt_sender/__init__.py
prompt_sender/main.py
prompt_sender-0.2.2.dist-info/LICENSE
prompt_sender-0.2.2.dist-info/METADATA
prompt_sender-0.2.2.dist-info/WHEEL
prompt_sender-0.2.2.dist-info/entry_points.txt
prompt_sender-0.2.2.dist-info/RECORD
