Metadata-Version: 2.1
Name: prompt-sender
Version: 0.2.2
Summary: Send prompts and model responses to the Argilla A/B testing platform for annotations
License: Apache 2.0 License
Author: Hannah Galbraith
Author-email: hannah.galbraith@bsc.es
Requires-Python: >=3.10,<3.13
Classifier: License :: Other/Proprietary License
Classifier: Programming Language :: Python :: 3
Classifier: Programming Language :: Python :: 3.10
Classifier: Programming Language :: Python :: 3.11
Classifier: Programming Language :: Python :: 3.12
Requires-Dist: argilla (>=2.1.0,<3.0.0)
Requires-Dist: typer (>=0.12.5,<0.13.0)
